medleydb_instruments/__init__.py
medleydb_instruments/multitrack.py
medleydb_instruments/resources/annotations/AClassicEducation_NightOwl_ACTIVATION_CONF.lab
medleydb_instruments/resources/annotations/AHa_TakeOnMe_ACTIVATION_CONF.lab
medleydb_instruments/resources/annotations/AcDc_BackInBlack_ACTIVATION_CONF.lab
medleydb_instruments/resources/annotations/Adele_SomeoneLikeYou_ACTIVATION_CONF.lab
medleydb_instruments/resources/annotations/Aerosmith_LoveInAnElevator_ACTIVATION_CONF.lab
medleydb_instruments/resources/annotations/AimeeNorwich_Child_ACTIVATION_CONF.lab
medleydb_instruments/resources/annotations/AimeeNorwich_Flying_ACTIVATION_CONF.lab
medleydb_instruments/resources/annotations/AlanisMorissette_YouOughtaKnow_ACTIVATION_CONF.lab
medleydb_instruments/resources/annotations/AlexanderRoss_GoodbyeBolero_ACTIVATION_CONF.lab
medleydb_instruments/resources/annotations/AlexanderRoss_VelvetCurtain_ACTIVATION_CONF.lab
medleydb_instruments/resources/annotations/AllThatRemains_Chiron_ACTIVATION_CONF.lab
medleydb_instruments/resources/annotations/AmarLal_Rest_ACTIVATION_CONF.lab
medleydb_instruments/resources/annotations/AmarLal_SpringDay1_ACTIVATION_CONF.lab
medleydb_instruments/resources/annotations/AnEndlessSporadic_Anything_ACTIVATION_CONF.lab
medleydb_instruments/resources/annotations/Anberlin_TheFeelGoodDrag_ACTIVATION_CONF.lab
medleydb_instruments/resources/annotations/ArcadeFire_BlackMirror_ACTIVATION_CONF.lab
medleydb_instruments/resources/annotations/ArcticMonkeys_Brainstorm_ACTIVATION_CONF.lab
medleydb_instruments/resources/annotations/Auctioneer_OurFutureFaces_ACTIVATION_CONF.lab
medleydb_instruments/resources/annotations/AvaLuna_Waterduct_ACTIVATION_CONF.lab
medleydb_instruments/resources/annotations/Bach10_01AchGottundHerr_ACTIVATION_CONF.lab
medleydb_instruments/resources/annotations/Bach10_02AchLiebenChristen_ACTIVATION_CONF.lab
medleydb_instruments/resources/annotations/Bach10_03ChristederdubistTagundLicht_ACTIVATION_CONF.lab
medleydb_instruments-1.0.1.dist-info/LICENSE
medleydb_instruments-1.0.1.dist-info/METADATA
medleydb_instruments-1.0.1.dist-info/WHEEL
medleydb_instruments-1.0.1.dist-info/RECORD
