Metadata-Version: 2.1
Name: medleydb-instruments
Version: 1.0.1
Summary: A tool to query MedleyDB annotations and metadata.
Home-page: https://github.com/Seon82/medleydb_instruments
License: MIT
Keywords: medleydb,instruments,music
Author: Dylan Sechet
Requires-Python: >=3.7,<4
Classifier: License :: OSI Approved :: MIT License
Classifier: Programming Language :: Python :: 3
Classifier: Programming Language :: Python :: 3.7
Classifier: Programming Language :: Python :: 3.8
Classifier: Programming Language :: Python :: 3.9
Classifier: Programming Language :: Python :: 3.10
Classifier: Programming Language :: Python :: 3.11
Requires-Dist: pandas (>=1.0.0,<2)
Project-URL: Repository, https://github.com/Seon82/medleydb_instruments
